thonnycontrib/monokai/__init__.py
thonny_monokai-0.1.1.dist-info/LICENSE
thonny_monokai-0.1.1.dist-info/METADATA
thonny_monokai-0.1.1.dist-info/WHEEL
thonny_monokai-0.1.1.dist-info/top_level.txt
thonny_monokai-0.1.1.dist-info/RECORD
