Metadata-Version: 2.1
Name: thonny-monokai
Version: 0.1.1
Summary: Monokai theme for Thonny
Author-email: Rodney Brown <rodneybbjr@gmail.com>
License: MIT License
Project-URL: Homepage, https://github.com/rodneybbjr/thonny-monokai
Project-URL: Download, https://github.com/rodneybbjr/thonny-monokai
Keywords: Thonny,monokai,IDE,education,dark,theme,programming
Classifier: Intended Audience :: Developers
Classifier: Intended Audience :: Education
Classifier: Intended Audience :: End Users/Desktop
Classifier: License :: OSI Approved :: MIT License
Classifier: Operating System :: MacOS
Classifier: Operating System :: Microsoft :: Windows
Classifier: Operating System :: POSIX
Classifier: Operating System :: POSIX :: Linux
Classifier: Operating System :: OS Independent
Classifier: Programming Language :: Python
Classifier: Programming Language :: Python :: 3
Classifier: Topic :: Education
Classifier: Topic :: Software Development
Classifier: Topic :: Software Development :: Embedded Systems
Requires-Python: >=3.0.0
License-File: LICENSE
Requires-Dist: thonny (>=3.0.0)
